bytecorecompiler/__init__.py
bytecorecompiler/compiler.py
bytecorecompiler/exception.py
bytecorecompiler/lexical_analysis.py
bytecorecompiler/parser.py
bytecorecompiler/py.typed
bytecorecompiler/semantic_analysis.py
bytecorecompiler/syntax.py
bytecorecompiler/syntax_analysis.py
bytecorecompiler/syntax_tree.py
bytecorecompiler-1.0.4.dist-info/LICENSE
bytecorecompiler-1.0.4.dist-info/METADATA
bytecorecompiler-1.0.4.dist-info/WHEEL
bytecorecompiler-1.0.4.dist-info/top_level.txt
bytecorecompiler-1.0.4.dist-info/RECORD
