Metadata-Version: 2.1
Name: bytecorecompiler
Version: 1.0.4
Summary: A compiler that transforms ByteCore assembly code into executable memory bytes, seamlessly bridging the gap between high-level assembly instructions and the ByteCore Emulator's low-level functionality.
Author-email: Joakim Winum Lien <joakim@winum.xyz>
Project-URL: Homepage, https://github.com/joakimwinum/bytecorecompiler
Project-URL: Bug Tracker, https://github.com/joakimwinum/bytecorecompiler/issues
Classifier: Programming Language :: Python :: 3
Classifier: License :: OSI Approved :: MIT License
Classifier: Operating System :: OS Independent
Requires-Python: >=3.11
License-File: LICENSE
Requires-Dist: bytecore ==1.1.2
